qexec/__init__.py
qexec/main.py
qexec-0.1.8.dist-info/METADATA
qexec-0.1.8.dist-info/WHEEL
qexec-0.1.8.dist-info/top_level.txt
qexec-0.1.8.dist-info/RECORD
