Metadata-Version: 2.1
Name: qexec
Version: 0.1.8
Summary: A package for executing commands through AI using qexec
Home-page: https://github.com/yourusername/qexec-ai
Author: Kiko
Author-email: your.email@example.com
Classifier: Programming Language :: Python :: 3
Classifier: License :: OSI Approved :: MIT License
Classifier: Operating System :: OS Independent
Requires-Python: >=3.6
Requires-Dist: cryptography
